py2json/__init__.py
py2json/main.py
pycodes2json-1.1.0.dist-info/METADATA
pycodes2json-1.1.0.dist-info/WHEEL
pycodes2json-1.1.0.dist-info/entry_points.txt
pycodes2json-1.1.0.dist-info/top_level.txt
pycodes2json-1.1.0.dist-info/RECORD
