Metadata-Version: 2.1
Name: pycodes2json
Version: 1.1.0
Summary: A tool to convert Python files to a JSON file.
Home-page: https://github.com/lechplace/py2json
Author: Lech Hubicki
Author-email: lech.hubicki@gmail.com
License: UNKNOWN
Platform: UNKNOWN
Classifier: Programming Language :: Python :: 3
Classifier: License :: OSI Approved :: MIT License
Classifier: Operating System :: OS Independent
Requires-Python: >=3.6
